{
    "meta": {
        "name": "ComponentPalette",
        "version": "1.0.0",
        "layout": "horizontal",
        "description": "Delphi-style horizontal component palette with categories"
    },
    "categories": [
        {
            "name": "⇄",
            "action": "toggleLayout",
            "items": []
        },
        {
            "name": "Standard",
            "items": [
                {
                    "type": "Panel",
                    "icon": "⬜",
                    "label": "Panel"
                },
                {
                    "type": "Button",
                    "icon": "🔘",
                    "label": "Button"
                },
                {
                    "type": "Label",
                    "icon": "📝",
                    "label": "Label"
                },
                {
                    "type": "Edit",
                    "icon": "✏️",
                    "label": "Edit"
                }
            ]
        },
        {
            "name": "Media",
            "items": [
                {
                    "type": "Image",
                    "icon": "🖼️",
                    "label": "Image"
                },
                {
                    "type": "Video",
                    "icon": "🎬",
                    "label": "Video"
                }
            ]
        },
        {
            "name": "Erweitert",
            "items": [
                {
                    "type": "Dropdown",
                    "icon": "📋",
                    "label": "Dropdown"
                },
                {
                    "type": "Checkbox",
                    "icon": "☑️",
                    "label": "Checkbox"
                },
                {
                    "type": "ColorPicker",
                    "icon": "🎨",
                    "label": "ColorPicker"
                },
                {
                    "type": "NumberInput",
                    "icon": "🔢",
                    "label": "NumberInput"
                },
                {
                    "type": "TabControl",
                    "icon": "📑",
                    "label": "TabControl"
                }
            ]
        },
        {
            "name": "Game",
            "items": [
                {
                    "type": "Sprite",
                    "icon": "🎯",
                    "label": "Sprite"
                },
                {
                    "type": "GameHeader",
                    "icon": "🎮",
                    "label": "GameHeader"
                },
                {
                    "type": "GameCard",
                    "icon": "🃏",
                    "label": "GameCard"
                }
            ]
        },
        {
            "name": "System",
            "items": [
                {
                    "type": "GameLoop",
                    "icon": "🔄",
                    "label": "GameLoop"
                },
                {
                    "type": "InputController",
                    "icon": "🎹",
                    "label": "InputController"
                },
                {
                    "type": "Timer",
                    "icon": "⏲️",
                    "label": "Timer"
                },
                {
                    "type": "Repeater",
                    "icon": "🔁",
                    "label": "Repeater"
                },
                {
                    "type": "SystemInfo",
                    "icon": "💻",
                    "label": "SystemInfo"
                },
                {
                    "type": "GameServer",
                    "icon": "🌐",
                    "label": "GameServer"
                },
                {
                    "type": "GameState",
                    "icon": "⏯️",
                    "label": "GameState"
                },
                {
                    "type": "StageController",
                    "icon": "🎬",
                    "label": "StageController"
                }
            ]
        },
        {
            "name": "Dialogs",
            "items": [
                {
                    "type": "DialogRoot",
                    "icon": "📄",
                    "label": "DialogRoot"
                },
                {
                    "type": "InfoWindow",
                    "icon": "ℹ️",
                    "label": "InfoWindow"
                },
                {
                    "type": "Toast",
                    "icon": "🔔",
                    "label": "Toast"
                },
                {
                    "type": "StatusBar",
                    "icon": "━",
                    "label": "StatusBar"
                },
                {
                    "type": "InspectorTemplate",
                    "icon": "📋",
                    "label": "InspectorDesigner"
                }
            ]
        }
    ]
}